netatmo/__init__.py
netatmo/netatmo.py
netatmo-1.0.7.dist-info/LICENSE
netatmo-1.0.7.dist-info/METADATA
netatmo-1.0.7.dist-info/WHEEL
netatmo-1.0.7.dist-info/entry_points.txt
netatmo-1.0.7.dist-info/top_level.txt
netatmo-1.0.7.dist-info/RECORD
