Metadata-Version: 2.1
Name: netatmo
Version: 1.0.7
Summary: Python3 API for the Netatmo Weather Station
Home-page: https://github.com/rene-d/netatmo
Author: Rene Devichi
Author-email: rene.github@gmail.com
License: UNKNOWN
Project-URL: Source, https://github.com/rene-d/netatmo
Project-URL: Bug Reports, https://github.com/rene-d/netatmo/issues
Keywords: development automation netatmo
Platform: UNKNOWN
Classifier: License :: Public Domain
Classifier: Programming Language :: Python :: 3.5
Classifier: Programming Language :: Python :: 3.6
Classifier: Programming Language :: Python :: 3.7
Classifier: Programming Language :: Python :: 3.8
Classifier: Programming Language :: Python :: 3.9
Requires-Python: >=3.5
Requires-Dist: requests
